tenauth/__init__.py
tenauth/fastapi.py
tenauth/schemas.py
tenauth/session.py
tenauth/tenancy.py
tenauth-0.1.3.dist-info/METADATA
tenauth-0.1.3.dist-info/WHEEL
tenauth-0.1.3.dist-info/top_level.txt
tenauth-0.1.3.dist-info/RECORD
