Metadata-Version: 2.4
Name: tenauth
Version: 0.1.3
Summary: Add your description here
Project-URL: Homepage, https://thwolter.github.io/tenauth/
Project-URL: Repository, https://github.com/thwolter/tenauth.git
Project-URL: Documentation, https://thwolter.github.io/tenauth/
Project-URL: Issues, https://github.com/thwolter/tenauth/issues/
Requires-Python: >=3.12
Requires-Dist: fastapi>=0.119.0
Requires-Dist: httpx>=0.28.1
Requires-Dist: mkdocs>=1.6.1
Requires-Dist: mkdocs-material>=9.6.21
Requires-Dist: pydantic>=2.12.0
Requires-Dist: sqlmodel>=0.0.27
